odoo/addons/purchase_request_type/README.rst
odoo/addons/purchase_request_type/__init__.py
odoo/addons/purchase_request_type/__manifest__.py
odoo/addons/purchase_request_type/data/purchase_request_type.xml
odoo/addons/purchase_request_type/i18n/purchase_request_type.pot
odoo/addons/purchase_request_type/models/__init__.py
odoo/addons/purchase_request_type/models/purchase_request.py
odoo/addons/purchase_request_type/models/purchase_request_type.py
odoo/addons/purchase_request_type/readme/CONFIGURE.rst
odoo/addons/purchase_request_type/readme/CONTRIBUTORS.rst
odoo/addons/purchase_request_type/readme/DESCRIPTION.rst
odoo/addons/purchase_request_type/readme/ROADMAP.rst
odoo/addons/purchase_request_type/readme/USAGE.rst
odoo/addons/purchase_request_type/security/ir.model.access.csv
odoo/addons/purchase_request_type/security/security.xml
odoo/addons/purchase_request_type/static/description/icon.png
odoo/addons/purchase_request_type/static/description/index.html
odoo/addons/purchase_request_type/tests/__init__.py
odoo/addons/purchase_request_type/tests/test_purchase_request_type.py
odoo/addons/purchase_request_type/views/purchase_request_type_view.xml
odoo/addons/purchase_request_type/views/purchase_request_view.xml
odoo14_addon_purchase_request_type-14.0.1.0.2.dist-info/METADATA
odoo14_addon_purchase_request_type-14.0.1.0.2.dist-info/WHEEL
odoo14_addon_purchase_request_type-14.0.1.0.2.dist-info/top_level.txt
odoo14_addon_purchase_request_type-14.0.1.0.2.dist-info/RECORD
